{
  "$schema": "https://raw.githubusercontent.com/microsoft/vcpkg-tool/main/docs/vcpkg.schema.json",
  "name": "arpam-gui",
  "version": "0.1",
  "dependencies": [
    "armadillo",
    "fftconv",
    "fmt",
    "gtest",
    "kfr",
    "qcustomplot",
    "qtbase",
    "rapidjson",
    "tbb",
    {
      "name": "opencv4",
      "platform": "x64",
      "features": [
        "tbb",
        "tiff",
        "world"
      ]
    },
    {
      "name": "opencv4",
      "platform": "!x64",
      "features": [
        "tiff",
        "world"
      ]
    },
    {
      "name": "fftw3",
      "platform": "x64",
      "features": [
        "avx2",
        "threads"
      ]
    },
    {
      "name": "fftw3",
      "platform": "!x64",
      "features": [
        "threads"
      ]
    }
  ],
  "builtin-baseline": "ae8fa5ae5e6162a88e412618245809ed2aa579d9"
}
